{"title":"自定义邮箱模板，邮箱回复，卡片模式","slug":"emailmd","date":"2021-01-23T13:52:05.000Z","updated":"2021-09-04T13:34:53.558Z","comments":true,"path":"api/articles/emailmd.json","excerpt":null,"covers":["https://cdn.jsdelivr.net/gh/Rr210/image@master/hexo/4/9dhaada.png","https://cdn.jsdelivr.net/gh/Rr210/image@master/hexo/4/9daihdadjadw.png"],"content":"<h2 id=\"1-仓库介绍\"><a href=\"#1-仓库介绍\" class=\"headerlink\" title=\"1.仓库介绍\"></a>1.仓库介绍</h2><blockquote>\n<p>此仓库为邮箱回复模板，卡片形式<br>使用请保留作者信息，谢谢⭐<br>仓库地址：【<a href=\"https://github.com/Rr210/emailformwork\">email</a>】</p>\n</blockquote>\n<ul>\n<li>我的博客地址：【<a href=\"https://u.mr90.top/\">Harry</a>】</li>\n</ul>\n<h2 id=\"2-演示图例\"><a href=\"#2-演示图例\" class=\"headerlink\" title=\"2.演示图例\"></a>2.演示图例</h2><details green><summary> <p>自定义通知邮件模板</p> </summary>\n              <div class='content'>\n              <p><img src=\"https://cdn.jsdelivr.net/gh/Rr210/image@master/hexo/4/9dhaada.png\"></p>\n              </div>\n            </details>\n\n<details green><summary> <p>自定义博主通知邮件主题</p> </summary>\n              <div class='content'>\n              <p><img src=\"https://cdn.jsdelivr.net/gh/Rr210/image@master/hexo/4/9daihdadjadw.png\"></p>\n              </div>\n            </details>\n\n<h2 id=\"3-模板介绍\"><a href=\"#3-模板介绍\" class=\"headerlink\" title=\"3.模板介绍\"></a>3.模板介绍</h2><ol>\n<li><code>index1.html</code>为自定义通知邮件模板</li>\n<li><code>index.html</code>为自定义博主通知邮件主题</li>\n<li><code>textarea</code>文件中自定义回复是以textarea标签写的，兼容性较差</li>\n</ol>\n<h2 id=\"4-模板使用\"><a href=\"#4-模板使用\" class=\"headerlink\" title=\"4.模板使用\"></a>4.模板使用</h2><ol>\n<li>此邮箱模块试用于【<a href=\"https://twikoo.js.org/\">twikoo</a>】等等</li>\n<li>修改<code>变量</code>可适配其他的评论框架</li>\n</ol>\n<h2 id=\"5-版权\"><a href=\"#5-版权\" class=\"headerlink\" title=\"5.版权\"></a>5.版权</h2><ul>\n<li>使用 <a href=\"https://github.com/Rr210/emailformwork/blob/master/LICENSE\">GPL V2.0</a> 协议开源。</li>\n</ul>\n","more":"<h2 id=\"1-仓库介绍\"><a href=\"#1-仓库介绍\" class=\"headerlink\" title=\"1.仓库介绍\"></a>1.仓库介绍</h2><blockquote>\n<p>此仓库为邮箱回复模板，卡片形式<br>使用请保留作者信息，谢谢⭐<br>仓库地址：【<a href=\"https://github.com/Rr210/emailformwork\">email</a>】</p>\n</blockquote>\n<ul>\n<li>我的博客地址：【<a href=\"https://u.mr90.top/\">Harry</a>】</li>\n</ul>\n<h2 id=\"2-演示图例\"><a href=\"#2-演示图例\" class=\"headerlink\" title=\"2.演示图例\"></a>2.演示图例</h2><details green><summary> <p>自定义通知邮件模板</p> </summary>\n              <div class='content'>\n              <p><img src=\"https://cdn.jsdelivr.net/gh/Rr210/image@master/hexo/4/9dhaada.png\"></p>\n              </div>\n            </details>\n\n<details green><summary> <p>自定义博主通知邮件主题</p> </summary>\n              <div class='content'>\n              <p><img src=\"https://cdn.jsdelivr.net/gh/Rr210/image@master/hexo/4/9daihdadjadw.png\"></p>\n              </div>\n            </details>\n\n<h2 id=\"3-模板介绍\"><a href=\"#3-模板介绍\" class=\"headerlink\" title=\"3.模板介绍\"></a>3.模板介绍</h2><ol>\n<li><code>index1.html</code>为自定义通知邮件模板</li>\n<li><code>index.html</code>为自定义博主通知邮件主题</li>\n<li><code>textarea</code>文件中自定义回复是以textarea标签写的，兼容性较差</li>\n</ol>\n<h2 id=\"4-模板使用\"><a href=\"#4-模板使用\" class=\"headerlink\" title=\"4.模板使用\"></a>4.模板使用</h2><ol>\n<li>此邮箱模块试用于【<a href=\"https://twikoo.js.org/\">twikoo</a>】等等</li>\n<li>修改<code>变量</code>可适配其他的评论框架</li>\n</ol>\n<h2 id=\"5-版权\"><a href=\"#5-版权\" class=\"headerlink\" title=\"5.版权\"></a>5.版权</h2><ul>\n<li>使用 <a href=\"https://github.com/Rr210/emailformwork/blob/master/LICENSE\">GPL V2.0</a> 协议开源。</li>\n</ul>\n","categories":[{"name":"技术·教程","path":"api/categories/技术·教程.json"}],"tags":[]}